easy_inference/__init__.py
easy_inference/providers/__init__.py
easy_inference/providers/provider_base.py
easy_inference/providers/realsense.py
easy_inference/providers/utils.py
easy_inference/providers/video.py
easy_inference/providers/webcam.py
easy_inference/utils/__init__.py
easy_inference/utils/boundingbox.py
easy_inference/utils/filters.py
easy_inference/utils/pad_frames.py
easy_inference/utils/ros_connector.py
easy_inference/utils/skeleton.py
easy_inference-0.1.1.dist-info/METADATA
easy_inference-0.1.1.dist-info/WHEEL
easy_inference-0.1.1.dist-info/top_level.txt
easy_inference-0.1.1.dist-info/RECORD
