Metadata-Version: 2.1
Name: easy-inference
Version: 0.1.1
Summary: Got a working detection model file? Want to quickly setup inference pipelines? You are in the right place!
Home-page: UNKNOWN
Author: Chadi Salmi
License: MIT
Platform: UNKNOWN
Classifier: Programming Language :: Python :: 3
Classifier: License :: OSI Approved :: MIT License
Requires-Python: >=3.8
Requires-Dist: numpy
Requires-Dist: opencv-python
Requires-Dist: pyrealsense2
Requires-Dist: scipy
Provides-Extra: ros
Requires-Dist: pyyaml ; extra == 'ros'
Requires-Dist: rospkg ; extra == 'ros'
